deephaven/__init__.py
deephaven/_dep.py
deephaven/_gc.py
deephaven/_jpy.py
deephaven/_query_scope.py
deephaven/_table_reader.py
deephaven/_udf.py
deephaven/_wrapper.py
deephaven/agg.py
deephaven/appmode.py
deephaven/arrow.py
deephaven/barrage.py
deephaven/calendar.py
deephaven/column.py
deephaven/concurrency_control.py
deephaven/constants.py
deephaven/csv.py
deephaven/dherror.py
deephaven/dtypes.py
deephaven/execution_context.py
deephaven/filters.py
deephaven/html.py
deephaven/jcompat.py
deephaven/liveness_scope.py
deephaven/numpy.py
deephaven/pandas.py
deephaven/parquet.py
deephaven/perfmon.py
deephaven/py.typed
deephaven/query_library.py
deephaven/replay.py
deephaven/systemic_obj_tracker.py
deephaven/table.py
deephaven/table_factory.py
deephaven/table_listener.py
deephaven/time.py
deephaven/update_graph.py
deephaven/updateby.py
deephaven/uri.py
deephaven/dbc/__init__.py
deephaven/dbc/adbc.py
deephaven/dbc/odbc.py
deephaven/experimental/__init__.py
deephaven/experimental/data_index.py
deephaven/experimental/ema.py
deephaven/experimental/iceberg.py
deephaven/experimental/outer_joins.py
deephaven/experimental/s3.py
deephaven/experimental/sql.py
deephaven/experimental/table_data_service.py
deephaven/json/__init__.py
deephaven/json/jackson.py
deephaven/learn/__init__.py
deephaven/learn/gather.py
deephaven/pandasplugin/__init__.py
deephaven/pandasplugin/pandas_as_table.py
deephaven/plot/__init__.py
deephaven/plot/axisformat.py
deephaven/plot/axistransform.py
deephaven/plot/color.py
deephaven/plot/figure.py
deephaven/plot/font.py
deephaven/plot/linestyle.py
deephaven/plot/plotstyle.py
deephaven/plot/selectable_dataset.py
deephaven/plot/shape.py
deephaven/server/__init__.py
deephaven/server/executors.py
deephaven/stream/__init__.py
deephaven/stream/table_publisher.py
deephaven/stream/kafka/__init__.py
deephaven/stream/kafka/cdc.py
deephaven/stream/kafka/consumer.py
deephaven/stream/kafka/producer.py
deephaven_internal/__init__.py
deephaven_internal/java_threads.py
deephaven_core-41.1.dist-info/METADATA
deephaven_core-41.1.dist-info/WHEEL
deephaven_core-41.1.dist-info/entry_points.txt
deephaven_core-41.1.dist-info/top_level.txt
deephaven_core-41.1.dist-info/RECORD
