Metadata-Version: 2.1
Name: deephaven-core
Version: 41.1
Summary: Deephaven Engine Python Package
Home-page: https://deephaven.io/
Author: Deephaven Data Labs
Author-email: python@deephaven.io
License: Deephaven Community License
Keywords: Deephaven Development
Classifier: Development Status :: 4 - Beta
Classifier: Intended Audience :: Developers
Classifier: Intended Audience :: Science/Research
Classifier: License :: Other/Proprietary License
Classifier: Programming Language :: Python
Classifier: Programming Language :: Python :: 3
Classifier: Programming Language :: Python :: 3 :: Only
Classifier: Programming Language :: Python :: 3.9
Classifier: Programming Language :: Python :: 3.10
Classifier: Programming Language :: Python :: 3.11
Classifier: Programming Language :: Python :: 3.12
Classifier: Programming Language :: Python :: 3.13
Requires-Python: >=3.9
Requires-Dist: jpy>=1.1.0
Requires-Dist: deephaven-plugin>=0.6.0
Requires-Dist: numpy
Requires-Dist: pandas>=1.5.0
Requires-Dist: pyarrow
Requires-Dist: numba; python_version < "3.13"
Provides-Extra: autocomplete
Requires-Dist: jedi==0.19.1; extra == "autocomplete"
Requires-Dist: docstring-parser>=0.16; extra == "autocomplete"
